{
  "id": "366773",
  "name": "NYCS - Z Train (pm rush): Broad Street → Jamaica Center–Parsons/Archer",
  "ref": "Z",
  "description": "Ruta real de metro urbano gestionada por Metropolitan Transportation Authority.",
  "distanceKm": 66.89,
  "elevationGain": 0.0,
  "elevationLoss": 0.0,
  "estWalkingSeconds": 53511,
  "estRunningSeconds": 21891,
  "stopsCount": 20,
  "coords": [
    [
      40.705816,
      -74.0113525,
      800.0
    ],
    [
      40.7059569,
      -74.0112981,
      800.0
    ],
    [
      40.7060971,
      -74.011228,
      800.0
    ],
    [
      40.7062491,
      -74.0111396,
      800.0
    ],
    [
      40.7070667,
      -74.0106466,
      800.0
    ],
    [
      40.7070497,
      -74.0105921,
      800.0
    ],
    [
      40.7062299,
      -74.0110851,
      800.0
    ],
    [
      40.7060828,
      -74.0111691,
      800.0
    ],
    [
      40.7059472,
      -74.0112368,
      800.0
    ],
    [
      40.7058054,
      -74.0112951,
      800.0
    ],
    [
      40.705816,
      -74.0113525,
      800.0
    ],
    [
      40.7097185,
      -74.0083131,
      800.0
    ],
    [
      40.709691,
      -74.0082649,
      800.0
    ],
    [
      40.7098337,
      -74.0081352,
      800.0
    ],
    [
      40.7099463,
      -74.0080329,
      800.0
    ],
    [
      40.710087,
      -74.0079035,
      800.0
    ],
    [
      40.710167,
      -74.0078262,
      800.0
    ],
    [
      40.7102579,
      -74.0077297,
      800.0
    ],
    [
      40.7102773,
      -74.0077109,
      800.0
    ],
    [
      40.7103832,
      -74.0075947,
      800.0
    ],
    [
      40.7105044,
      -74.007451,
      800.0
    ],
    [
      40.710603,
      -74.0073213,
      800.0
    ],
    [
      40.7107454,
      -74.0071322,
      800.0
    ],
    [
      40.7108113,
      -74.0070435,
      800.0
    ],
    [
      40.710827,
      -74.0070226,
      800.0
    ],
    [
      40.710858,
      -74.0070621,
      800.0
    ],
    [
      40.7106746,
      -74.0073073,
      800.0
    ],
    [
      40.7105362,
      -74.0074855,
      800.0
    ],
    [
      40.710421,
      -74.0076301,
      800.0
    ],
    [
      40.7102785,
      -74.0077839,
      800.0
    ],
    [
      40.7102832,
      -74.0077894,
      800.0
    ],
    [
      40.7103137,
      -74.0078287,
      800.0
    ],
    [
      40.7102451,
      -74.0078903,
      800.0
    ],
    [
      40.7102174,
      -74.007848,
      800.0
    ],
    [
      40.7100022,
      -74.008055,
      800.0
    ],
    [
      40.7097966,
      -74.00824,
      800.0
    ],
    [
      40.7097185,
      -74.0083131,
      800.0
    ],
    [
      40.7125357,
      -74.0041086,
      800.0
    ],
    [
      40.7128995,
      -74.0037583,
      800.0
    ],
    [
      40.713605,
      -74.0030788,
      800.0
    ],
    [
      40.7136286,
      -74.0031226,
      800.0
    ],
    [
      40.7130022,
      -74.0037245,
      800.0
    ],
    [
      40.7125618,
      -74.0041497,
      800.0
    ],
    [
      40.7125357,
      -74.0041086,
      800.0
    ],
    [
      40.7185505,
      -73.9996949,
      800.0
    ],
    [
      40.7185368,
      -73.9996661,
      800.0
    ],
    [
      40.7184889,
      -73.9997091,
      800.0
    ],
    [
      40.7175912,
      -74.0004322,
      800.0
    ],
    [
      40.7174393,
      -74.0005486,
      800.0
    ],
    [
      40.7174543,
      -74.0005823,
      800.0
    ],
    [
      40.7176076,
      -74.0004702,
      800.0
    ],
    [
      40.7185011,
      -73.999738,
      800.0
    ],
    [
      40.7185505,
      -73.9996949,
      800.0
    ],
    [
      40.7200929,
      -73.9930259,
      800.0
    ],
    [
      40.7200622,
      -73.9930429,
      800.0
    ],
    [
      40.7204038,
      -73.9941628,
      800.0
    ],
    [
      40.7207005,
      -73.9950394,
      800.0
    ],
    [
      40.7207305,
      -73.9950218,
      800.0
    ],
    [
      40.7204339,
      -73.9941452,
      800.0
    ],
    [
      40.7200929,
      -73.9930259,
      800.0
    ],
    [
      40.7186197,
      -73.9884428,
      800.0
    ],
    [
      40.7186483,
      -73.9884274,
      800.0
    ],
    [
      40.7186281,
      -73.9883359,
      800.0
    ],
    [
      40.7186132,
      -73.9882834,
      800.0
    ],
    [
      40.7185858,
      -73.9881925,
      800.0
    ],
    [
      40.7185444,
      -73.9880542,
      800.0
    ],
    [
      40.7184897,
      -73.9878709,
      800.0
    ],
    [
      40.7184408,
      -73.9877045,
      800.0
    ],
    [
      40.718377,
      -73.987492,
      800.0
    ],
    [
      40.7183044,
      -73.9872461,
      800.0
    ],
    [
      40.7182542,
      -73.9870785,
      800.0
    ],
    [
      40.7181962,
      -73.9868832,
      800.0
    ],
    [
      40.7181496,
      -73.9867295,
      800.0
    ],
    [
      40.7181014,
      -73.9865905,
      800.0
    ],
    [
      40.7180815,
      -73.9865366,
      800.0
    ],
    [
      40.718051,
      -73.9865516,
      800.0
    ],
    [
      40.7180717,
      -73.9866224,
      800.0
    ],
    [
      40.7181213,
      -73.9867904,
      800.0
    ],
    [
      40.7181728,
      -73.9869621,
      800.0
    ],
    [
      40.7182328,
      -73.9871626,
      800.0
    ],
    [
      40.7182787,
      -73.9873167,
      800.0
    ],
    [
      40.7183011,
      -73.9873912,
      800.0
    ],
    [
      40.7183394,
      -73.9875212,
      800.0
    ],
    [
      40.7183858,
      -73.9876783,
      800.0
    ],
    [
      40.7184317,
      -73.9878319,
      800.0
    ],
    [
      40.7184721,
      -73.9879667,
      800.0
    ],
    [
      40.7185146,
      -73.9881092,
      800.0
    ],
    [
      40.7185752,
      -73.9883133,
      800.0
    ],
    [
      40.7185804,
      -73.9883127,
      800.0
    ],
    [
      40.7185912,
      -73.9883486,
      800.0
    ],
    [
      40.7186197,
      -73.9884428,
      800.0
    ],
    [
      40.7080053,
      -73.9568871,
      800.0
    ],
    [
      40.7086018,
      -73.9586051,
      800.0
    ],
    [
      40.708572,
      -73.9586213,
      800.0
    ],
    [
      40.7079803,
      -73.9569021,
      800.0
    ],
    [
      40.7080053,
      -73.9568871,
      800.0
    ],
    [
      40.6969601,
      -73.9352486,
      800.0
    ],
    [
      40.6975804,
      -73.9363453,
      800.0
    ],
    [
      40.697661,
      -73.9364817,
      800.0
    ],
    [
      40.6976432,
      -73.9365029,
      800.0
    ],
    [
      40.6975959,
      -73.9364464,
      800.0
    ],
    [
      40.6975478,
      -73.9363774,
      800.0
    ],
    [
      40.696925,
      -73.9352824,
      800.0
    ],
    [
      40.6968759,
      -73.9351911,
      800.0
    ],
    [
      40.69684,
      -73.9351187,
      800.0
    ],
    [
      40.6967732,
      -73.9349774,
      800.0
    ],
    [
      40.6967965,
      -73.9349558,
      800.0
    ],
    [
      40.6969601,
      -73.9352486,
      800.0
    ],
    [
      40.6899831,
      -73.9230886,
      800.0
    ],
    [
      40.6890987,
      -73.9215438,
      800.0
    ],
    [
      40.6891205,
      -73.9215221,
      800.0
    ],
    [
      40.690005,
      -73.9230668,
      800.0
    ],
    [
      40.6899831,
      -73.9230886,
      800.0
    ],
    [
      40.683274,
      -73.9112881,
      800.0
    ],
    [
      40.6824035,
      -73.9097618,
      800.0
    ],
    [
      40.6824254,
      -73.9097401,
      800.0
    ],
    [
      40.6832959,
      -73.9112664,
      800.0
    ],
    [
      40.683274,
      -73.9112881,
      800.0
    ],
    [
      40.6799193,
      -73.9052759,
      800.0
    ],
    [
      40.6789743,
      -73.9036309,
      800.0
    ],
    [
      40.6789385,
      -73.9036667,
      800.0
    ],
    [
      40.6798925,
      -73.9053002,
      800.0
    ],
    [
      40.6799193,
      -73.9052759,
      800.0
    ],
    [
      40.6779081,
      -73.8926674,
      800.0
    ],
    [
      40.6781983,
      -73.8907157,
      800.0
    ],
    [
      40.678158,
      -73.8907053,
      800.0
    ],
    [
      40.6778678,
      -73.8926569,
      800.0
    ],
    [
      40.6779081,
      -73.8926674,
      800.0
    ],
    [
      40.6816933,
      -73.8790086,
      800.0
    ],
    [
      40.6815222,
      -73.8796164,
      800.0
    ],
    [
      40.68141,
      -73.8800125,
      800.0
    ],
    [
      40.681144,
      -73.8808458,
      800.0
    ],
    [
      40.6811765,
      -73.8808649,
      800.0
    ],
    [
      40.6814426,
      -73.8800314,
      800.0
    ],
    [
      40.6815655,
      -73.8796388,
      800.0
    ],
    [
      40.6817369,
      -73.87903,
      800.0
    ],
    [
      40.6816933,
      -73.8790086,
      800.0
    ],
    [
      40.6829884,
      -73.8746253,
      800.0
    ],
    [
      40.68295,
      -73.8746063,
      800.0
    ],
    [
      40.6834683,
      -73.8727803,
      800.0
    ],
    [
      40.6835068,
      -73.8727993,
      800.0
    ],
    [
      40.6829884,
      -73.8746253,
      800.0
    ],
    [
      40.6914209,
      -73.8662176,
      800.0
    ],
    [
      40.691395,
      -73.8662054,
      800.0
    ],
    [
      40.6913307,
      -73.8665953,
      800.0
    ],
    [
      40.6911303,
      -73.8679224,
      800.0
    ],
    [
      40.6910984,
      -73.8681338,
      800.0
    ],
    [
      40.6911228,
      -73.8681402,
      800.0
    ],
    [
      40.6911547,
      -73.8679288,
      800.0
    ],
    [
      40.6913552,
      -73.8666017,
      800.0
    ],
    [
      40.6914209,
      -73.8662176,
      800.0
    ],
    [
      40.6941525,
      -73.8505245,
      800.0
    ],
    [
      40.6940973,
      -73.8507269,
      800.0
    ],
    [
      40.693998,
      -73.8510463,
      800.0
    ],
    [
      40.6939103,
      -73.8512991,
      800.0
    ],
    [
      40.6938784,
      -73.8513889,
      800.0
    ],
    [
      40.6934754,
      -73.8524695,
      800.0
    ],
    [
      40.693495,
      -73.8524822,
      800.0
    ],
    [
      40.6939301,
      -73.8513115,
      800.0
    ],
    [
      40.6940181,
      -73.8510578,
      800.0
    ],
    [
      40.6941177,
      -73.8507373,
      800.0
    ],
    [
      40.6941731,
      -73.8505343,
      800.0
    ],
    [
      40.6941525,
      -73.8505245,
      800.0
    ],
    [
      40.6951266,
      -73.8432987,
      800.0
    ],
    [
      40.6951086,
      -73.8450847,
      800.0
    ],
    [
      40.695103,
      -73.8452882,
      800.0
    ],
    [
      40.6951249,
      -73.8452893,
      800.0
    ],
    [
      40.6951305,
      -73.8450854,
      800.0
    ],
    [
      40.6951486,
      -73.8432991,
      800.0
    ],
    [
      40.6951266,
      -73.8432987,
      800.0
    ],
    [
      40.7002636,
      -73.8292293,
      800.0
    ],
    [
      40.7005768,
      -73.8273437,
      800.0
    ],
    [
      40.7005982,
      -73.8273499,
      800.0
    ],
    [
      40.700285,
      -73.8292355,
      800.0
    ],
    [
      40.7002636,
      -73.8292293,
      800.0
    ],
    [
      40.7001865,
      -73.8088547,
      800.0
    ],
    [
      40.7001758,
      -73.8088488,
      800.0
    ],
    [
      40.7002588,
      -73.8085793,
      800.0
    ],
    [
      40.700772,
      -73.8068063,
      800.0
    ],
    [
      40.7008039,
      -73.8068195,
      800.0
    ],
    [
      40.7005557,
      -73.8078017,
      800.0
    ],
    [
      40.7004217,
      -73.8082152,
      800.0
    ],
    [
      40.7002907,
      -73.8085961,
      800.0
    ],
    [
      40.7001865,
      -73.8088547,
      800.0
    ],
    [
      40.70235,
      -73.8002547,
      800.0
    ],
    [
      40.7022484,
      -73.8006665,
      800.0
    ],
    [
      40.7018291,
      -73.8023647,
      800.0
    ],
    [
      40.7018951,
      -73.8023932,
      800.0
    ],
    [
      40.7023145,
      -73.8006972,
      800.0
    ],
    [
      40.7024166,
      -73.8002844,
      800.0
    ],
    [
      40.70235,
      -73.8002547,
      800.0
    ],
    [
      40.7125267,
      -74.0040945,
      800.0
    ],
    [
      40.7124483,
      -74.0041932,
      800.0
    ],
    [
      40.7123838,
      -74.0043094,
      800.0
    ],
    [
      40.71225,
      -74.004615,
      800.0
    ],
    [
      40.7121083,
      -74.0049405,
      800.0
    ],
    [
      40.7119898,
      -74.0052366,
      800.0
    ],
    [
      40.7118583,
      -74.0055115,
      800.0
    ],
    [
      40.7117477,
      -74.0057126,
      800.0
    ],
    [
      40.7116183,
      -74.0059083,
      800.0
    ],
    [
      40.7112678,
      -74.0063921,
      800.0
    ],
    [
      40.7110157,
      -74.00674,
      800.0
    ],
    [
      40.7108139,
      -74.0070103,
      800.0
    ],
    [
      40.710613,
      -74.0072844,
      800.0
    ],
    [
      40.710489,
      -74.0074384,
      800.0
    ],
    [
      40.7103685,
      -74.0075785,
      800.0
    ],
    [
      40.7100793,
      -74.0078798,
      800.0
    ],
    [
      40.7099383,
      -74.008008,
      800.0
    ],
    [
      40.7098257,
      -74.0081103,
      800.0
    ],
    [
      40.7096763,
      -74.0082441,
      800.0
    ],
    [
      40.7095655,
      -74.0083539,
      800.0
    ],
    [
      40.709049,
      -74.0088758,
      800.0
    ],
    [
      40.7086646,
      -74.0093146,
      800.0
    ],
    [
      40.7085481,
      -74.0094314,
      800.0
    ],
    [
      40.7076092,
      -74.0102738,
      800.0
    ],
    [
      40.7074136,
      -74.0104334,
      800.0
    ],
    [
      40.7072023,
      -74.0105851,
      800.0
    ],
    [
      40.7070723,
      -74.0106634,
      800.0
    ],
    [
      40.7125267,
      -74.0040945,
      800.0
    ],
    [
      40.7135971,
      -74.0030638,
      800.0
    ],
    [
      40.7141053,
      -74.0025871,
      800.0
    ],
    [
      40.7142606,
      -74.0024684,
      800.0
    ],
    [
      40.714423,
      -74.0023746,
      800.0
    ],
    [
      40.7145817,
      -74.0023005,
      800.0
    ],
    [
      40.7149003,
      -74.0021829,
      800.0
    ],
    [
      40.7150563,
      -74.0021108,
      800.0
    ],
    [
      40.7152161,
      -74.0019978,
      800.0
    ],
    [
      40.7156086,
      -74.0017118,
      800.0
    ],
    [
      40.7160178,
      -74.0014653,
      800.0
    ],
    [
      40.7164103,
      -74.0011793,
      800.0
    ],
    [
      40.716615,
      -74.001056,
      800.0
    ],
    [
      40.7168197,
      -74.0009327,
      800.0
    ],
    [
      40.7170247,
      -74.0007965,
      800.0
    ],
    [
      40.717234,
      -74.0006688,
      800.0
    ],
    [
      40.7174324,
      -74.0005329,
      800.0
    ],
    [
      40.7175844,
      -74.0004163,
      800.0
    ],
    [
      40.7184817,
      -73.9996934,
      800.0
    ],
    [
      40.7185294,
      -73.9996509,
      800.0
    ],
    [
      40.718664,
      -73.9995321,
      800.0
    ],
    [
      40.7188797,
      -73.9993143,
      800.0
    ],
    [
      40.7190325,
      -73.9991743,
      800.0
    ],
    [
      40.7198346,
      -73.9985264,
      800.0
    ],
    [
      40.7207869,
      -73.9976911,
      800.0
    ],
    [
      40.7208893,
      -73.9975899,
      800.0
    ],
    [
      40.720979,
      -73.9974696,
      800.0
    ],
    [
      40.7210542,
      -73.9973329,
      800.0
    ],
    [
      40.721113,
      -73.997183,
      800.0
    ],
    [
      40.7211541,
      -73.9970231,
      800.0
    ],
    [
      40.7211767,
      -73.9968569,
      800.0
    ],
    [
      40.7211802,
      -73.9966882,
      800.0
    ],
    [
      40.7211645,
      -73.9965206,
      800.0
    ],
    [
      40.72113,
      -73.996358,
      800.0
    ],
    [
      40.7206878,
      -73.9950469,
      800.0
    ],
    [
      40.7200494,
      -73.9930499,
      800.0
    ],
    [
      40.719693,
      -73.9918895,
      800.0
    ],
    [
      40.7196306,
      -73.9916841,
      800.0
    ],
    [
      40.7194944,
      -73.9912358,
      800.0
    ],
    [
      40.7194238,
      -73.9910032,
      800.0
    ],
    [
      40.7188321,
      -73.9890563,
      800.0
    ],
    [
      40.7186339,
      -73.9883194,
      800.0
    ],
    [
      40.7181571,
      -73.9867105,
      800.0
    ],
    [
      40.7180921,
      -73.9865209,
      800.0
    ],
    [
      40.7179916,
      -73.986314,
      800.0
    ],
    [
      40.7177792,
      -73.9859536,
      800.0
    ],
    [
      40.7176893,
      -73.9857358,
      800.0
    ],
    [
      40.7176096,
      -73.9855133,
      800.0
    ],
    [
      40.7175791,
      -73.985413,
      800.0
    ],
    [
      40.7154743,
      -73.9784383,
      800.0
    ],
    [
      40.710402,
      -73.961723,
      800.0
    ],
    [
      40.7102485,
      -73.9612215,
      800.0
    ],
    [
      40.7101832,
      -73.9610538,
      800.0
    ],
    [
      40.7101265,
      -73.9609264,
      800.0
    ],
    [
      40.7100198,
      -73.9607593,
      800.0
    ],
    [
      40.7099301,
      -73.9606394,
      800.0
    ],
    [
      40.7089738,
      -73.9594585,
      800.0
    ],
    [
      40.7088754,
      -73.9593179,
      800.0
    ],
    [
      40.7088025,
      -73.959159,
      800.0
    ],
    [
      40.7086034,
      -73.9585845,
      800.0
    ],
    [
      40.7080165,
      -73.9568905,
      800.0
    ],
    [
      40.707931,
      -73.956631,
      800.0
    ],
    [
      40.7077066,
      -73.9558551,
      800.0
    ],
    [
      40.7075405,
      -73.9553655,
      800.0
    ],
    [
      40.7074986,
      -73.9552464,
      800.0
    ],
    [
      40.707455,
      -73.9551198,
      800.0
    ],
    [
      40.7073708,
      -73.9548733,
      800.0
    ],
    [
      40.7065384,
      -73.9524583,
      800.0
    ],
    [
      40.7064171,
      -73.9521113,
      800.0
    ],
    [
      40.7062686,
      -73.9517378,
      800.0
    ],
    [
      40.7061214,
      -73.9514426,
      800.0
    ],
    [
      40.7053424,
      -73.9500464,
      800.0
    ],
    [
      40.7038648,
      -73.9474275,
      800.0
    ],
    [
      40.7032497,
      -73.9463281,
      800.0
    ],
    [
      40.7017316,
      -73.9435722,
      800.0
    ],
    [
      40.701494,
      -73.9431563,
      800.0
    ],
    [
      40.7012965,
      -73.9428254,
      800.0
    ],
    [
      40.7007285,
      -73.9419141,
      800.0
    ],
    [
      40.698635,
      -73.9382172,
      800.0
    ],
    [
      40.6978927,
      -73.9368724,
      800.0
    ],
    [
      40.6976637,
      -73.9364683,
      800.0
    ],
    [
      40.6968116,
      -73.9349504,
      800.0
    ],
    [
      40.6967531,
      -73.9348454,
      800.0
    ],
    [
      40.6966678,
      -73.9346909,
      800.0
    ],
    [
      40.6965956,
      -73.9345709,
      800.0
    ],
    [
      40.6964526,
      -73.9343111,
      800.0
    ],
    [
      40.6963594,
      -73.9341714,
      800.0
    ],
    [
      40.6962857,
      -73.9340774,
      800.0
    ],
    [
      40.6961929,
      -73.9339356,
      800.0
    ],
    [
      40.6961586,
      -73.933877,
      800.0
    ],
    [
      40.6937432,
      -73.929608,
      800.0
    ],
    [
      40.6933869,
      -73.9289783,
      800.0
    ],
    [
      40.6928738,
      -73.9280735,
      800.0
    ],
    [
      40.6906351,
      -73.9241285,
      800.0
    ],
    [
      40.6900126,
      -73.9230335,
      800.0
    ],
    [
      40.6895552,
      -73.9222288,
      800.0
    ],
    [
      40.689145,
      -73.9215088,
      800.0
    ],
    [
      40.6867814,
      -73.9173711,
      800.0
    ],
    [
      40.6863255,
      -73.916573,
      800.0
    ],
    [
      40.6859193,
      -73.915852,
      800.0
    ],
    [
      40.683742,
      -73.9120204,
      800.0
    ],
    [
      40.6832979,
      -73.9112418,
      800.0
    ],
    [
      40.6824508,
      -73.9097455,
      800.0
    ],
    [
      40.6811945,
      -73.9075491,
      800.0
    ],
    [
      40.6805847,
      -73.9064725,
      800.0
    ],
    [
      40.6803141,
      -73.905996,
      800.0
    ],
    [
      40.6801776,
      -73.905753,
      800.0
    ],
    [
      40.6800982,
      -73.9056297,
      800.0
    ],
    [
      40.6798793,
      -73.9053154,
      800.0
    ],
    [
      40.6792649,
      -73.904274,
      800.0
    ],
    [
      40.6789306,
      -73.9036853,
      800.0
    ],
    [
      40.6789133,
      -73.9036556,
      800.0
    ],
    [
      40.678807,
      -73.9034737,
      800.0
    ],
    [
      40.6785397,
      -73.9030162,
      800.0
    ],
    [
      40.6782955,
      -73.9025961,
      800.0
    ],
    [
      40.6780386,
      -73.9021582,
      800.0
    ],
    [
      40.677877,
      -73.9018756,
      800.0
    ],
    [
      40.6776579,
      -73.901498,
      800.0
    ],
    [
      40.6774285,
      -73.9011216,
      800.0
    ],
    [
      40.6772828,
      -73.9008695,
      800.0
    ],
    [
      40.6769444,
      -73.9002849,
      800.0
    ],
    [
      40.6768665,
      -73.9001272,
      800.0
    ],
    [
      40.67683,
      -73.900024,
      800.0
    ],
    [
      40.6768056,
      -73.8999169,
      800.0
    ],
    [
      40.6767932,
      -73.8998012,
      800.0
    ],
    [
      40.6767971,
      -73.8997089,
      800.0
    ],
    [
      40.6768182,
      -73.8996303,
      800.0
    ],
    [
      40.6771102,
      -73.8976707,
      800.0
    ],
    [
      40.6772593,
      -73.8966371,
      800.0
    ],
    [
      40.6776725,
      -73.8938799,
      800.0
    ],
    [
      40.677856,
      -73.8926411,
      800.0
    ],
    [
      40.6781416,
      -73.8907131,
      800.0
    ],
    [
      40.6782289,
      -73.8901396,
      800.0
    ],
    [
      40.6782616,
      -73.8899369,
      800.0
    ],
    [
      40.6783012,
      -73.8897545,
      800.0
    ],
    [
      40.6783531,
      -73.8895535,
      800.0
    ],
    [
      40.6785056,
      -73.8890732,
      800.0
    ],
    [
      40.6790179,
      -73.8874656,
      800.0
    ],
    [
      40.6795932,
      -73.8856557,
      800.0
    ],
    [
      40.6801685,
      -73.8838458,
      800.0
    ],
    [
      40.6806027,
      -73.8825105,
      800.0
    ],
    [
      40.6810405,
      -73.8811259,
      800.0
    ],
    [
      40.6811328,
      -73.8808366,
      800.0
    ],
    [
      40.6813969,
      -73.8800084,
      800.0
    ],
    [
      40.6815035,
      -73.879627,
      800.0
    ],
    [
      40.6816122,
      -73.8792394,
      800.0
    ],
    [
      40.681679,
      -73.8790058,
      800.0
    ],
    [
      40.6822932,
      -73.876854,
      800.0
    ],
    [
      40.6828004,
      -73.8750716,
      800.0
    ],
    [
      40.6829367,
      -73.8745927,
      800.0
    ],
    [
      40.6834477,
      -73.8727699,
      800.0
    ],
    [
      40.6834823,
      -73.8726476,
      800.0
    ],
    [
      40.6835169,
      -73.872559,
      800.0
    ],
    [
      40.6835685,
      -73.8724666,
      800.0
    ],
    [
      40.6836132,
      -73.8724072,
      800.0
    ],
    [
      40.6836708,
      -73.8723513,
      800.0
    ],
    [
      40.683739,
      -73.8723003,
      800.0
    ],
    [
      40.6838446,
      -73.8722562,
      800.0
    ],
    [
      40.6839498,
      -73.8722404,
      800.0
    ],
    [
      40.6840456,
      -73.8722569,
      800.0
    ],
    [
      40.684567,
      -73.872426,
      800.0
    ],
    [
      40.6849713,
      -73.8725436,
      800.0
    ],
    [
      40.686286,
      -73.872947,
      800.0
    ],
    [
      40.6870903,
      -73.8732283,
      800.0
    ],
    [
      40.6874055,
      -73.8733247,
      800.0
    ],
    [
      40.6888386,
      -73.8738302,
      800.0
    ],
    [
      40.6889161,
      -73.8738567,
      800.0
    ],
    [
      40.6889914,
      -73.8738688,
      800.0
    ],
    [
      40.6890746,
      -73.8738676,
      800.0
    ],
    [
      40.6891541,
      -73.87385,
      800.0
    ],
    [
      40.689207,
      -73.8738259,
      800.0
    ],
    [
      40.6892781,
      -73.8737883,
      800.0
    ],
    [
      40.689338,
      -73.8737361,
      800.0
    ],
    [
      40.6893959,
      -73.8736758,
      800.0
    ],
    [
      40.6894559,
      -73.8735843,
      800.0
    ],
    [
      40.6895497,
      -73.8733942,
      800.0
    ],
    [
      40.6896351,
      -73.8731936,
      800.0
    ],
    [
      40.6901501,
      -73.8719834,
      800.0
    ],
    [
      40.6901988,
      -73.8718604,
      800.0
    ],
    [
      40.6902295,
      -73.87178,
      800.0
    ],
    [
      40.6903077,
      -73.8715522,
      800.0
    ],
    [
      40.6903915,
      -73.8712392,
      800.0
    ],
    [
      40.691005,
      -73.8688256,
      800.0
    ],
    [
      40.6910718,
      -73.8685234,
      800.0
    ],
    [
      40.6911392,
      -73.8681426,
      800.0
    ],
    [
      40.6914306,
      -73.8662271,
      800.0
    ],
    [
      40.6917926,
      -73.86409,
      800.0
    ],
    [
      40.6920679,
      -73.8625063,
      800.0
    ],
    [
      40.6922696,
      -73.8610046,
      800.0
    ],
    [
      40.6924323,
      -73.8598487,
      800.0
    ],
    [
      40.6924613,
      -73.8595451,
      800.0
    ],
    [
      40.6924857,
      -73.8592101,
      800.0
    ],
    [
      40.6924977,
      -73.8589837,
      800.0
    ],
    [
      40.6925445,
      -73.8581418,
      800.0
    ],
    [
      40.6926183,
      -73.856935,
      800.0
    ],
    [
      40.6926887,
      -73.8555751,
      800.0
    ],
    [
      40.692742,
      -73.8550355,
      800.0
    ],
    [
      40.6928055,
      -73.8546389,
      800.0
    ],
    [
      40.6928909,
      -73.8542701,
      800.0
    ],
    [
      40.6930082,
      -73.8538726,
      800.0
    ],
    [
      40.6931361,
      -73.8534951,
      800.0
    ],
    [
      40.6935127,
      -73.8524716,
      800.0
    ],
    [
      40.6939532,
      -73.8513015,
      800.0
    ],
    [
      40.6940395,
      -73.8510513,
      800.0
    ],
    [
      40.694134,
      -73.8507425,
      800.0
    ],
    [
      40.6941861,
      -73.8505456,
      800.0
    ],
    [
      40.6942148,
      -73.8504349,
      800.0
    ],
    [
      40.6942978,
      -73.85006,
      800.0
    ],
    [
      40.6945981,
      -73.848531,
      800.0
    ],
    [
      40.6947025,
      -73.8479877,
      800.0
    ],
    [
      40.6948826,
      -73.8470502,
      800.0
    ],
    [
      40.6949294,
      -73.8468203,
      800.0
    ],
    [
      40.6950435,
      -73.8462067,
      800.0
    ],
    [
      40.6950964,
      -73.8458344,
      800.0
    ],
    [
      40.6951265,
      -73.845508,
      800.0
    ],
    [
      40.6951401,
      -73.8452872,
      800.0
    ],
    [
      40.695146,
      -73.8450824,
      800.0
    ],
    [
      40.6951632,
      -73.8433123,
      800.0
    ],
    [
      40.6951691,
      -73.8427086,
      800.0
    ],
    [
      40.6951779,
      -73.8423363,
      800.0
    ],
    [
      40.6952044,
      -73.8417908,
      800.0
    ],
    [
      40.6952388,
      -73.8413224,
      800.0
    ],
    [
      40.6952686,
      -73.8410059,
      800.0
    ],
    [
      40.6953253,
      -73.8405555,
      800.0
    ],
    [
      40.6953775,
      -73.8402071,
      800.0
    ],
    [
      40.6954291,
      -73.8399371,
      800.0
    ],
    [
      40.6954757,
      -73.8397435,
      800.0
    ],
    [
      40.6955817,
      -73.8393793,
      800.0
    ],
    [
      40.6956422,
      -73.8392003,
      800.0
    ],
    [
      40.6957163,
      -73.8390109,
      800.0
    ],
    [
      40.6958475,
      -73.8387182,
      800.0
    ],
    [
      40.6959451,
      -73.8385186,
      800.0
    ],
    [
      40.6960441,
      -73.8383461,
      800.0
    ],
    [
      40.6962996,
      -73.8379459,
      800.0
    ],
    [
      40.6969972,
      -73.8369232,
      800.0
    ],
    [
      40.6973501,
      -73.8364021,
      800.0
    ],
    [
      40.6974885,
      -73.8361881,
      800.0
    ],
    [
      40.6976282,
      -73.8359464,
      800.0
    ],
    [
      40.6978691,
      -73.8355066,
      800.0
    ],
    [
      40.6981292,
      -73.8350331,
      800.0
    ],
    [
      40.698705,
      -73.8339645,
      800.0
    ],
    [
      40.6992989,
      -73.832891,
      800.0
    ],
    [
      40.699393,
      -73.8327145,
      800.0
    ],
    [
      40.6994892,
      -73.8325114,
      800.0
    ],
    [
      40.6996193,
      -73.8321848,
      800.0
    ],
    [
      40.6997226,
      -73.8318784,
      800.0
    ],
    [
      40.6998113,
      -73.8315499,
      800.0
    ],
    [
      40.7000273,
      -73.830665,
      800.0
    ],
    [
      40.7001236,
      -73.8302542,
      800.0
    ],
    [
      40.7002487,
      -73.8295847,
      800.0
    ],
    [
      40.7003047,
      -73.8292263,
      800.0
    ],
    [
      40.7006131,
      -73.8273646,
      800.0
    ],
    [
      40.7006513,
      -73.827125,
      800.0
    ],
    [
      40.7007999,
      -73.8262155,
      800.0
    ],
    [
      40.7008935,
      -73.8257247,
      800.0
    ],
    [
      40.7009759,
      -73.8253596,
      800.0
    ],
    [
      40.7011043,
      -73.8248816,
      800.0
    ],
    [
      40.7013179,
      -73.8240759,
      800.0
    ],
    [
      40.7013601,
      -73.8238779,
      800.0
    ],
    [
      40.701395,
      -73.823667,
      800.0
    ],
    [
      40.7014107,
      -73.8234782,
      800.0
    ],
    [
      40.7014122,
      -73.8232319,
      800.0
    ],
    [
      40.7014048,
      -73.8230141,
      800.0
    ],
    [
      40.7013823,
      -73.8227741,
      800.0
    ],
    [
      40.701337,
      -73.8225407,
      800.0
    ],
    [
      40.7012844,
      -73.8223408,
      800.0
    ],
    [
      40.7012248,
      -73.8221574,
      800.0
    ],
    [
      40.7011759,
      -73.8220244,
      800.0
    ],
    [
      40.7010991,
      -73.8218481,
      800.0
    ],
    [
      40.7009522,
      -73.8215821,
      800.0
    ],
    [
      40.7008406,
      -73.8214191,
      800.0
    ],
    [
      40.7007184,
      -73.8212628,
      800.0
    ],
    [
      40.7002386,
      -73.8206691,
      800.0
    ],
    [
      40.6996798,
      -73.8198733,
      800.0
    ],
    [
      40.6995481,
      -73.8196553,
      800.0
    ],
    [
      40.6994145,
      -73.8194191,
      800.0
    ],
    [
      40.6992765,
      -73.8191509,
      800.0
    ],
    [
      40.6991513,
      -73.8188823,
      800.0
    ],
    [
      40.6990469,
      -73.8186401,
      800.0
    ],
    [
      40.6989721,
      -73.8184626,
      800.0
    ],
    [
      40.6988952,
      -73.8182713,
      800.0
    ],
    [
      40.6988156,
      -73.8180664,
      800.0
    ],
    [
      40.698752,
      -73.8178794,
      800.0
    ],
    [
      40.6986911,
      -73.8176943,
      800.0
    ],
    [
      40.698645,
      -73.8175402,
      800.0
    ],
    [
      40.6985974,
      -73.8173372,
      800.0
    ],
    [
      40.6985581,
      -73.8171525,
      800.0
    ],
    [
      40.6985323,
      -73.8169648,
      800.0
    ],
    [
      40.6985088,
      -73.8167798,
      800.0
    ],
    [
      40.6984943,
      -73.8165944,
      800.0
    ],
    [
      40.6984836,
      -73.8164086,
      800.0
    ],
    [
      40.6984496,
      -73.8152688,
      800.0
    ],
    [
      40.6984499,
      -73.8151486,
      800.0
    ],
    [
      40.6984519,
      -73.8150585,
      800.0
    ],
    [
      40.6984595,
      -73.8149425,
      800.0
    ],
    [
      40.6984744,
      -73.8148262,
      800.0
    ],
    [
      40.6984926,
      -73.8147108,
      800.0
    ],
    [
      40.6985133,
      -73.8145953,
      800.0
    ],
    [
      40.6985345,
      -73.8144762,
      800.0
    ],
    [
      40.6985562,
      -73.8143631,
      800.0
    ],
    [
      40.6985824,
      -73.8142452,
      800.0
    ],
    [
      40.6986086,
      -73.8141355,
      800.0
    ],
    [
      40.6994253,
      -73.8112812,
      800.0
    ],
    [
      40.6999644,
      -73.8093194,
      800.0
    ],
    [
      40.6999949,
      -73.8092329,
      800.0
    ],
    [
      40.700048,
      -73.8091155,
      800.0
    ],
    [
      40.7000978,
      -73.8090105,
      800.0
    ],
    [
      40.7001631,
      -73.8088422,
      800.0
    ],
    [
      40.7002246,
      -73.8086414,
      800.0
    ],
    [
      40.7002458,
      -73.8085724,
      800.0
    ],
    [
      40.7007034,
      -73.8069936,
      800.0
    ],
    [
      40.700759,
      -73.8068007,
      800.0
    ],
    [
      40.7011348,
      -73.8052974,
      800.0
    ],
    [
      40.7011779,
      -73.805151,
      800.0
    ],
    [
      40.701489,
      -73.8040154,
      800.0
    ],
    [
      40.7016358,
      -73.8032668,
      800.0
    ],
    [
      40.7017754,
      -73.8025236,
      800.0
    ],
    [
      40.7018159,
      -73.8023592,
      800.0
    ],
    [
      40.7022353,
      -73.8006603,
      800.0
    ]
  ],
  "stops": [
    {
      "id": "7638896785",
      "name": "Broad Street",
      "lat": 40.7070723,
      "lon": -74.0106634,
      "role": "stop"
    },
    {
      "id": "2052618419",
      "name": "Fulton Street",
      "lat": 40.7108139,
      "lon": -74.0070103,
      "role": "stop"
    },
    {
      "id": "7639625987",
      "name": "Chambers Street",
      "lat": 40.7135971,
      "lon": -74.0030638,
      "role": "stop"
    },
    {
      "id": "7638896796",
      "name": "Canal Street",
      "lat": 40.7185294,
      "lon": -73.9996509,
      "role": "stop"
    },
    {
      "id": "7638896804",
      "name": "Bowery",
      "lat": 40.7200494,
      "lon": -73.9930499,
      "role": "stop"
    },
    {
      "id": "7639610806",
      "name": "Essex Street",
      "lat": 40.7181571,
      "lon": -73.9867105,
      "role": "stop"
    },
    {
      "id": "7526971434",
      "name": "Marcy Avenue",
      "lat": 40.7080165,
      "lon": -73.9568905,
      "role": "stop"
    },
    {
      "id": "8401244134",
      "name": "Myrtle Avenue",
      "lat": 40.6968116,
      "lon": -73.9349504,
      "role": "stop"
    },
    {
      "id": "7526995859",
      "name": "Gates Avenue",
      "lat": 40.689145,
      "lon": -73.9215088,
      "role": "stop"
    },
    {
      "id": "7526995863",
      "name": "Chauncey Street",
      "lat": 40.6824508,
      "lon": -73.9097455,
      "role": "stop"
    },
    {
      "id": "6613053540",
      "name": "Broadway Junction",
      "lat": 40.6789306,
      "lon": -73.9036853,
      "role": "stop"
    },
    {
      "id": "7526995867",
      "name": "Van Siclen Avenue",
      "lat": 40.6781416,
      "lon": -73.8907131,
      "role": "stop"
    },
    {
      "id": "7526995870",
      "name": "Norwood Avenue",
      "lat": 40.681679,
      "lon": -73.8790058,
      "role": "stop"
    },
    {
      "id": "7526995872",
      "name": "Crescent Street",
      "lat": 40.6834477,
      "lon": -73.8727699,
      "role": "stop"
    },
    {
      "id": "7527016797",
      "name": "75th Street–Elderts Lane",
      "lat": 40.6914306,
      "lon": -73.8662271,
      "role": "stop"
    },
    {
      "id": "7526995877",
      "name": "Woodhaven Boulevard",
      "lat": 40.6941861,
      "lon": -73.8505456,
      "role": "stop"
    },
    {
      "id": "7526995879",
      "name": "104th Street",
      "lat": 40.6951632,
      "lon": -73.8433123,
      "role": "stop"
    },
    {
      "id": "5302313022",
      "name": "121st Street",
      "lat": 40.7006131,
      "lon": -73.8273646,
      "role": "stop"
    },
    {
      "id": "5302312614",
      "name": "Sutphin Boulevard–Archer Avenue–JFK Airport",
      "lat": 40.7007034,
      "lon": -73.8069936,
      "role": "stop"
    },
    {
      "id": "5302312612",
      "name": "Jamaica Center–Parsons/Archer",
      "lat": 40.7022353,
      "lon": -73.8006603,
      "role": "stop"
    }
  ]
}